psidata/__init__.py
psidata/api.py
psidata/bcolz_tools.py
psidata/calibration.py
psidata/legacy_bcolz_tools.py
psidata/recording.py
psidata/signal.py
psidata/version.py
psidata/zarr_tools.py
psidata-0.1.11.dist-info/LICENSE.txt
psidata-0.1.11.dist-info/METADATA
psidata-0.1.11.dist-info/WHEEL
psidata-0.1.11.dist-info/top_level.txt
psidata-0.1.11.dist-info/RECORD
