Metadata-Version: 2.1
Name: psidata
Version: 0.1.11
Summary: Lightweight wrapper for managing psiexperiment data
Author-email: Brad Buran <bburan@alum.mit.edu>, Brad Buran <buran@ohsu.edu>, "Buran Consulting, LLC" <info@bradburan.com>
Maintainer-email: Brad Buran <bburan@alum.mit.edu>, Brad Buran <buran@ohsu.edu>, "Buran Consulting, LLC" <info@bradburan.com>
License: MIT License
Requires-Python: >=3.7
License-File: LICENSE.txt
Requires-Dist: numpy
Requires-Dist: pandas
Requires-Dist: pyyaml
Provides-Extra: bcolz-backend
Requires-Dist: bcolz ; extra == 'bcolz-backend'
Provides-Extra: docs
Requires-Dist: sphinx ; extra == 'docs'
Requires-Dist: sphinx-rtd-theme ; extra == 'docs'
Provides-Extra: legacy-bcolz-backend
Requires-Dist: blosc ; extra == 'legacy-bcolz-backend'
Provides-Extra: test
Requires-Dist: pytest ; extra == 'test'
Requires-Dist: pytest-console-scripts ; extra == 'test'
Provides-Extra: zarr-backend
Requires-Dist: zarr ; extra == 'zarr-backend'
